<?xml version="1.0" encoding="UTF-8" standalone="yes"?>
<SensorPairs>
    <SensorPair>
        <innerSensor>2</innerSensor>
        <outerSensor>1</outerSensor>
        <innerSectionID>1</innerSectionID>
        <outerSectionID>-1</outerSectionID>
    </SensorPair>
    <SensorPair>
        <innerSensor>3</innerSensor>
        <outerSensor>4</outerSensor>
        <innerSectionID>1</innerSectionID>
        <outerSectionID>2</outerSectionID>
    </SensorPair>
    <SensorPair>
        <innerSensor>5</innerSensor>
        <outerSensor>6</outerSensor>
        <innerSectionID>3</innerSectionID>
        <outerSectionID>-1</outerSectionID>
    </SensorPair>
</SensorPairs>